mxrv_define.v
//**********************************************
// define and macros
//**********************************************

// port width declare
`define PORT_WORD_WIDTH  31:0
`define WORD_WIDTH  32
`define BYTES_IN_A_WORD 4

mxrv_pc_reg.v
//**************************************************
// mxrv_pc_reg.v
// function: PC指针变化逻辑
// case1: 默认状态，一拍，PC指针地址偏移+4
// case2: 增加hold状态，此状态下PC指针保持，流水线暂停
// case3: 地址跳转，此状态下PC直接装在送过来的地址
//**************************************************

module mxrv_pc_reg (
    input   clk,
    input   rst_n,
    // case2 use
    input   hold_flag_i,
    // case3 use
    input   jump_flag_i,
    input [`PORT_WORD_WIDTH]  jump_addr_i,

    // output
    output [`PORT_WORD_WIDTH]    pc_o
);

    reg [`PORT_WORD_WIDTH]   pc_reg;

    assign pc_o = pc_reg;

    always @(posedge clk or negedge rst_n) begin
        // reset logic
        if(!rst_n) begin
            pc_reg <= 0;
        end
        // hold logic
        else if(hold_flag_i) begin
            pc_reg <= pc_reg;
        end
        // jump logic
        else if(jump_flag_i) begin
            pc_reg <= jump_addr_i;
        end
        // case1 logic
        else begin
            pc_reg <= pc_reg + `BYTES_IN_A_WORD;
        end
    end
    
endmodule

mxrv_top_tb.sv
//*****************************************
// mxrv_top_tb.sv
// function: provide module instance and basic test
//*****************************************
`timescale 1ns/1ps

`include "mxrv_define.v"
`include "mxrv_pc_reg.v"

module mxrv_top_tb ();

    reg clk;
    reg rst_n;

    // jump signals
    reg jump_flag;
    reg [`PORT_WORD_WIDTH]  jump_addr;

    // hold signals
    reg hold_flag;

    // pc_reg output
    wire [`PORT_WORD_WIDTH] pc_wire_out;
    
    // instance pc_reg
    mxrv_pc_reg u_pc_reg (
        .clk(clk),
        .rst_n(rst_n),
        // case2 use 
        .hold_flag_i(hold_flag),
        // case3 use
        .jump_flag_i(jump_flag),
        .jump_addr_i(jump_addr)
    );

    // clk logic
    initial begin
        clk = 0;
        forever begin
            #10;
            clk = ~clk;
        end
    end

    // rst_n logic
    initial begin
        rst_n = 0;
        #100;
        rst_n = 1;
    end

    // case1 normal pc = pc + 4

    // case2 hold
    initial begin
        hold_flag = 0;
        #1000;
        hold_flag = 1;
        #2000;
        hold_flag = 0;
        #3000;
        hold_flag = 1;
        #4000;
        hold_flag = 0;
    end

    // case3 jump
    initial begin
        jump_flag = 0;
        jump_addr = 0;
        #4500;
        jump_flag = 1;
        jump_addr = $urandom;
        repeat(2) begin
            @(negedge clk);
        end
        jump_flag = 0;
        jump_addr = 0;
    end

    // sim timeout
    initial begin
        #500000
        $display("Time Out.");
        $finish;
    end

    // generate wave file, used by gtkwave
    initial begin
        $dumpfile("mxrv_top_tb.vcd");
        $dumpvars(0, mxrv_top_tb);
    end

endmodule

mxrv_top_tb.vcd
$date
	Thu Jun  6 23:11:54 2024
$end
$version
	Icarus Verilog
$end
$timescale
	1ps
$end
$scope module mxrv_top_tb $end
$var reg 1 ! clk $end
$var reg 1 " hold_flag $end
$var reg 32 # jump_addr [31:0] $end
$var reg 1 $ jump_flag $end
$var reg 1 % rst_n $end
$scope module u_pc_reg $end
$var wire 1 ! clk $end
$var wire 1 " hold_flag_i $end
$var wire 32 & jump_addr_i [31:0] $end
$var wire 1 $ jump_flag_i $end
$var wire 32 ' pc_o [31:0] $end
$var wire 1 % rst_n $end
$var reg 32 ( pc_reg [31:0] $end
$upscope $end
$upscope $end
$enddefinitions $end
#0
$dumpvars
b0 (
b0 '
b0 &
0%
0$
b0 #
0"
0!
$end
#10000
1!
#20000
0!
#30000
1!
#40000
0!
#50000
1!
#60000
0!
#70000
1!
#80000
0!
#90000
1!
#100000
0!
1%
#110000
b100 '
b100 (
1!
#120000
0!
#130000
b1000 '
b1000 (
1!
#140000
0!
#150000
b1100 '
b1100 (
1!
#160000
0!
#170000
b10000 '
b10000 (
1!
#180000
0!
#190000
b10100 '
b10100 (
1!
#200000
0!
#210000
b11000 '
b11000 (
1!
#220000
0!
#230000
b11100 '
b11100 (
1!
#240000
0!
#250000
b100000 '
b100000 (
1!
#260000
0!
#270000
b100100 '
b100100 (
1!
#280000
0!
#290000
b101000 '
b101000 (
1!
#300000
0!
#310000
b101100 '
b101100 (
1!
#320000
0!
#330000
b110000 '
b110000 (
1!
#340000
0!
#350000
b110100 '
b110100 (
1!
#360000
0!
#370000
b111000 '
b111000 (
1!
#380000
0!
#390000
b111100 '
b111100 (
1!
#400000
0!
#410000
b1000000 '
b1000000 (
1!
#420000
0!
#430000
b1000100 '
b1000100 (
1!
#440000
0!
#450000
b1001000 '
b1001000 (
1!
#460000
0!
#470000
b1001100 '
b1001100 (
1!
#480000
0!
#490000
b1010000 '
b1010000 (
1!
#500000
0!
#510000
b1010100 '
b1010100 (
1!
#520000
0!
#530000
b1011000 '
b1011000 (
1!
#540000
0!
#550000
b1011100 '
b1011100 (
1!
#560000
0!
#570000
b1100000 '
b1100000 (
1!
#580000
0!
#590000
b1100100 '
b1100100 (
1!
#600000
0!
#610000
b1101000 '
b1101000 (
1!
#620000
0!
#630000
b1101100 '
b1101100 (
1!
#640000
0!
#650000
b1110000 '
b1110000 (
1!
#660000
0!
#670000
b1110100 '
b1110100 (
1!
#680000
0!
#690000
b1111000 '
b1111000 (
1!
#700000
0!
#710000
b1111100 '
b1111100 (
1!
#720000
0!
#730000
b10000000 '
b10000000 (
1!
#740000
0!
#750000
b10000100 '
b10000100 (
1!
#760000
0!
#770000
b10001000 '
b10001000 (
1!
#780000
0!
#790000
b10001100 '
b10001100 (
1!
#800000
0!
#810000
b10010000 '
b10010000 (
1!
#820000
0!
#830000
b10010100 '
b10010100 (
1!
#840000
0!
#850000
b10011000 '
b10011000 (
1!
#860000
0!
#870000
b10011100 '
b10011100 (
1!
#880000
0!
#890000
b10100000 '
b10100000 (
1!
#900000
0!
#910000
b10100100 '
b10100100 (
1!
#920000
0!
#930000
b10101000 '
b10101000 (
1!
#940000
0!
#950000
b10101100 '
b10101100 (
1!
#960000
0!
#970000
b10110000 '
b10110000 (
1!
#980000
0!
#990000
b10110100 '
b10110100 (
1!
#1000000
0!
1"
