mxrv_define.v
//**********************************************
// define and macros
//**********************************************

// sequential logic
`define RstEnable  1'b0
`define RstDisable  1'b1

// port width declare
`define PORT_WORD_WIDTH 31:0
`define WORD_WIDTH      32
`define BYTES_IN_A_WORD 4

// CSRRegBus
`define CsrRegAddrBus   11:0
`define RegBus  31:0
`define DoubleRegBus    63:0

// Common Value
`define ZeroByte    8'h0
`define ZeroWord    32'h0
`define ErrorWord   32'hffff_ffff
`define ZeroDouble  64'h0


// CSR parameter support
`define RV32I   32'h4000_0100
`define SingleHart  32'h1
`define Write   1'b1
`define Read    1'b0


// CSR REG addr list
`define CSR_FFLAGS  12'h001
`define CSR_FRM     12'h002
`define CSR_FCSR    12'h003
`define CSR_MSTATUS 12'h300
`define CSR_MISA    12'h301
`define CSR_MIE     12'h304
`define CSR_MTVEC   12'h305
`define CSR_MSCRATCH    12'h340
`define CSR_MEPC    12'h341
`define CSR_MCAUSE  12'h342
`define CSR_MTVAL   12'h343
`define CSR_MIP     12'h344
`define CSR_MCYCLE  12'hB00
`define CSR_MCYCLEH 12'hB80
`define CSR_MINSTRET    12'hB02
`define CSR_MINSTRETH   12'hB82
`define CSR_MVENDORID   12'hF11
`define CSR_MARCHID 12'hF12
`define CSR_MIMPID  12'hF13
`define CSR_MHARTID 12'hF14

mxrv_csr_reg.v
//**********************************
// csr_reg
// funtion:
// RV32标准控制寄存器实现————实现读写寄存器操作
// 只能读而不能写的寄存器无需在写指令中实现功能
// 需要定义大量宏以提高可读性
// 参考文档应当包含书籍或官方文档

module mxrv_csr_reg (
    // for rd or wr to sychronized register
    input clk,
    input rst_n,
    // inst, if csr related, execute. Otherwise no effect
    input[`PORT_WORD_WIDTH] inst_i,
    // 读写寄存器一套接口
    input[`CsrRegAddrBus] csr_addr_i,
    input   we_i,
    input[`RegBus]  csr_wdata_i,
    output reg[`RegBus] csr_rdata_o,
    // 状态寄存器必要信号
    input   inst_succ_flag
    );

    // 浮点累计异常
    reg[`RegBus] fflags;
    // 浮点动态舍入模式
    reg[`RegBus] frm;
    // 浮点控制状态寄存器
    reg[`RegBus] fcsr;
    // 机器模式下状态寄存器
    reg[`RegBus] mstatus;
    // 指示当前处理器支持架构特性
    reg[`RegBus] misa;
    // 控制不同类型中断局部屏蔽
    reg[`RegBus] mie;
    // 配置异常的入口地址
    reg[`RegBus] mtvec;
    // 机器模式下程序临时保存某些数据
    reg[`RegBus] mscratch;
    // 保存进入异常之前的PC值
    reg[`RegBus] mepc;
    // 保存进入异常前的出错原因，最高一位为中断域，低31位为异常编号
    reg[`RegBus] mcause;
    // 保存进入异常前的出错指令编码值
    reg[`RegBus] mtval;
    // 查询终端等待状态
    reg[`RegBus] mip;
    // 反应处理器执行了多少个时钟，共64位
    wire[`RegBus] mcycle;
    wire[`RegBus] mcycleh;
    // 反应处理器成功执行的指令数目，可用于衡量处理器性能
    wire[`RegBus] minstret;
    wire[`RegBus] minstreth;
    // 只读，供应商编号，为0，为非商业处理器
    reg[`RegBus] mvendorid;
    // 只读，微架构编号，为0，未实现
    reg[`RegBus] marchid;
    // 只读，硬件实现编号，为0，未实现
    reg[`RegBus] mimpid;
    // 只读，hartID
    reg[`RegBus] mhartid;
    // 计时器，配合mtimecmp的值以产生中断，按理来说需要放在其他位置
    // 标准RISC-V没有给他们的规定地址
    reg[`RegBus] mtime;
    reg[`RegBus] mtimecmp;
    reg[`RegBus] msip;

    // cycle and instret
    reg[`DoubleRegBus]  cycle,instret;
    assign mcycle = cycle[31:0];
    assign mcycleh = cycle[63:32];
    assign minstret = instret[31:0];
    assign minstreth = instret[63:32];
    

    // 周期计数: 时钟，复位，cycle寄存器
    always @(posedge clk or negedge rst_n) begin
        if(rst_n == `RstEnable) begin
            //{mcycleh, mcycle} <= `ZeroDouble;
            cycle <= `ZeroDouble;
        end else begin
            //{mcycleh, mcycle} <= {mcycleh, mcycleh} + 1'b1;
            cycle <= cycle + 1'b1;
        end
    end

    // 指令成功计数：时钟，复位，指令执行成功信号，instret寄存器
    always @(posedge clk or negedge rst_n) begin
        if(rst_n == `RstEnable) begin
            //{minstreth, minstret} <= `ZeroDouble;
            instret <= `ZeroDouble;
        end else begin
            if (inst_succ_flag) begin
                //{minstreth, minstret} <= {minstreth, minstret} + 1'b1;
                instret <= instret + 1'b1;
            end else begin
                //{minstreth, minstret} <= {minstreth, minstret};
                instret <= instret;
            end
        end
    end

    // 读写寄存器逻辑
    // 初始化所有CSR寄存器，需要同步时钟，复位，写请求有效，CSR寄存器地址，写数据
    // we_i为`Read状态时为读，在下个周期返回数据到总线上
    // 同步时钟，复位，读寄存器地址，输出读数据
    always @(posedge clk or negedge rst_n) begin
        if(rst_n == `RstEnable) begin
            // 读写寄存器初始化
            fflags <= `ZeroWord;
            frm <= `ZeroWord;
            fcsr <= `ZeroWord;
            mstatus <= `ZeroWord;
            mie <= `ZeroWord;
            mtvec <= `ZeroWord;
            mscratch <= `ZeroWord;
            mepc <= `ZeroWord;
            mcause <= `ZeroWord;
            mtval <=`ZeroWord;
            mip <= `ZeroWord;
            // 只读寄存器初始化
            // 32位指令集支持
            misa <= `RV32I;
            mvendorid <= `ZeroWord;
            marchid <= `ZeroWord;
            mimpid <= `ZeroWord;
            // 暂不支持超线程技术，仅单核处理器实现
            mhartid <= `SingleHart;
            // 读输出初始化
            csr_rdata_o <= `ZeroWord;
        end else begin
            if (we_i == `Write) begin
                case (csr_addr_i)
                    `CSR_FFLAGS: begin
                        fflags <= csr_wdata_i;
                    end
                    `CSR_FRM: begin
                        frm <= csr_wdata_i;
                    end
                    `CSR_FCSR: begin
                        fcsr <= csr_wdata_i;
                    end
                    `CSR_MSTATUS: begin
                        mstatus <= csr_wdata_i;
                    end
                    `CSR_MIE: begin
                        mie <= csr_wdata_i;
                    end
                    `CSR_MTVEC: begin
                        mtvec <= csr_wdata_i;
                    end
                    `CSR_MSCRATCH: begin
                        mscratch <= csr_wdata_i;
                    end
                    `CSR_MEPC: begin
                        mepc <= csr_wdata_i;
                    end
                    `CSR_MCAUSE: begin
                        mcause <= csr_wdata_i;
                    end
                    `CSR_MTVAL: begin
                        mtval <= csr_wdata_i;
                    end
                    `CSR_MIP: begin
                        mip <= csr_wdata_i;
                    end
                    default: begin
                        csr_rdata_o <= `ErrorWord;
                    end
                endcase
            end else begin
                case (csr_addr_i)
                    `CSR_FFLAGS: begin
                        csr_rdata_o <= fflags;
                    end
                    `CSR_FRM: begin
                        csr_rdata_o <= frm;
                    end
                    `CSR_FCSR: begin
                        csr_rdata_o <= fcsr;
                    end
                    `CSR_MSTATUS: begin
                        csr_rdata_o <= mstatus;
                    end
                    `CSR_MISA: begin
                        csr_rdata_o <= misa;
                    end
                    `CSR_MIE: begin
                        csr_rdata_o <= mie;
                    end
                    `CSR_MTVEC: begin
                        csr_rdata_o <= mtvec;
                    end
                    `CSR_MSCRATCH: begin
                        csr_rdata_o <= mscratch;
                    end
                    `CSR_MEPC: begin
                        csr_rdata_o <= mepc;
                    end
                    `CSR_MCAUSE: begin
                        csr_rdata_o <= mcause;
                    end
                    `CSR_MTVAL: begin
                        csr_rdata_o <= mtval;
                    end
                    `CSR_MIP: begin
                        csr_rdata_o <= mip;
                    end
                    `CSR_MCYCLE: begin
                        csr_rdata_o <= mcycle;
                    end
                    `CSR_MCYCLEH: begin
                        csr_rdata_o <= mcycleh;
                    end
                    `CSR_MINSTRET: begin
                        csr_rdata_o <= minstret;
                    end
                    `CSR_MINSTRETH: begin
                        csr_rdata_o <= minstreth;
                    end
                    `CSR_MVENDORID: begin
                        csr_rdata_o <= mvendorid;
                    end
                    `CSR_MARCHID: begin
                        csr_rdata_o <= marchid;
                    end
                    `CSR_MIMPID: begin
                        csr_rdata_o <= mimpid;
                    end
                    `CSR_MHARTID: begin
                        csr_rdata_o <= mhartid;
                    end


                    
                    default: begin
                        csr_rdata_o <= `ErrorWord;
                    end
                endcase
            end
        end
    end



    
endmodule

mxrv_pc_reg.v
//**************************************************
// mxrv_pc_reg.v
// function: PC指针变化逻辑
// case1: 默认状态，一拍，PC指针地址偏移+4
// case2: 增加hold状态，此状态下PC指针保持，流水线暂停
// case3: 地址跳转，此状态下PC直接装在送过来的地址
//**************************************************

module mxrv_pc_reg (
    input   clk,
    input   rst_n,
    // case2 use
    input   hold_flag_i,
    // case3 use
    input   jump_flag_i,
    input [`PORT_WORD_WIDTH]  jump_addr_i,

    // output
    output [`PORT_WORD_WIDTH]    pc_o
);

    reg [`PORT_WORD_WIDTH]   pc_reg;

    assign pc_o = pc_reg;

    always @(posedge clk or negedge rst_n) begin
        // reset logic
        if(!rst_n) begin
            pc_reg <= 0;
        end
        // hold logic
        else if(hold_flag_i) begin
            pc_reg <= pc_reg;
        end
        // jump logic
        else if(jump_flag_i) begin
            pc_reg <= jump_addr_i;
        end
        // case1 logic
        else begin
            pc_reg <= pc_reg + `BYTES_IN_A_WORD;
        end
    end
    
endmodule

mxrv_top_tb.sv
//*****************************************
// mxrv_top_tb.sv
// function: provide module instance and basic test
//*****************************************
`timescale 1ns/1ps

`include "mxrv_define.v"
`include "mxrv_pc_reg.v"
`include "mxrv_csr_reg.v"

module mxrv_top_tb ();

    reg clk;
    reg rst_n;

    // jump signals
    reg jump_flag;
    reg [`PORT_WORD_WIDTH]  jump_addr;

    // hold signals
    reg hold_flag;

    // pc_reg output
    wire [`PORT_WORD_WIDTH] pc_wire_out;

    // csr_reg ports
    reg[`CsrRegAddrBus] csr_addr;
    reg we;
    reg[`RegBus]    csr_wdata;
    wire[`RegBus]   csr_rdata;
    
    // instance pc_reg
    mxrv_pc_reg u_pc_reg (
        .clk(clk),
        .rst_n(rst_n),
        // case2 use 
        .hold_flag_i(hold_flag),
        // case3 use
        .jump_flag_i(jump_flag),
        .jump_addr_i(jump_addr)
    );

    // instance csr_reg
    mxrv_csr_reg u_csr_reg (
        .clk(clk),
        .rst_n(rst_n),
        .csr_addr_i(csr_addr),
        .csr_wdata_i(csr_wdata),
        .we_i(we),
        .csr_rdata_o(csr_rdata)
    );

    // clk logic
    initial begin
        clk = 0;
        forever begin
            #10;
            clk = ~clk;
        end
    end

    // rst_n logic
    initial begin
        #10;
        rst_n = 0;
        #90;
        rst_n = 1;
    end

    // case1 normal pc = pc + 4

    // case2 hold
    initial begin
        hold_flag = 0;
        #1000;
        hold_flag = 1;
        #2000;
        hold_flag = 0;
        #3000;
        hold_flag = 1;
        #4000;
        hold_flag = 0;
    end

    // case3 jump
    initial begin
        jump_flag = 0;
        jump_addr = 0;
        #4500;
        jump_flag = 1;
        jump_addr = $urandom;
        repeat(2) begin
            @(negedge clk);
        end
        jump_flag = 0;
        jump_addr = 0;
    end


    // CSR_REG READ OR WRITE TEST
    initial begin
        we = `Read;
        csr_wdata = `ZeroWord;
        csr_addr = `ZeroWord;
        #5000;
        fork
            begin: READ
                #100;
                we = `Read;
                csr_addr = `CSR_MISA;
            end
            begin: WRITE
                #300;
                we = `Write;
                csr_addr = `CSR_MSTATUS;
                csr_wdata = $urandom;
            end
            begin: CHECK
                #400;
                we = `Read;
                csr_addr = `CSR_MSTATUS;
            end
        join
    end

    // sim timeout
    initial begin
        #10000
        $display("Time Out.");
        $finish;
    end

    // generate wave file, used by gtkwave
    initial begin
        $dumpfile("mxrv_top_tb.vcd");
        $dumpvars(0, mxrv_top_tb);
    end

endmodule

mxrv_top_tb.vcd
$date
	Tue Jun 11 15:53:02 2024
$end
$version
	Icarus Verilog
$end
$timescale
	1ps
$end
$scope module mxrv_top_tb $end
$var wire 32 ! csr_rdata [31:0] $end
$var reg 1 " clk $end
$var reg 12 # csr_addr [11:0] $end
$var reg 32 $ csr_wdata [31:0] $end
$var reg 1 % hold_flag $end
$var reg 32 & jump_addr [31:0] $end
$var reg 1 ' jump_flag $end
$var reg 1 ( rst_n $end
$var reg 1 ) we $end
$scope module u_csr_reg $end
$var wire 1 " clk $end
$var wire 12 * csr_addr_i [11:0] $end
$var wire 32 + csr_wdata_i [31:0] $end
$var wire 32 , inst_i [31:0] $end
$var wire 1 - inst_succ_flag $end
$var wire 1 ( rst_n $end
$var wire 1 ) we_i $end
$var wire 32 . minstreth [31:0] $end
$var wire 32 / minstret [31:0] $end
$var wire 32 0 mcycleh [31:0] $end
$var wire 32 1 mcycle [31:0] $end
$var reg 32 2 csr_rdata_o [31:0] $end
$var reg 64 3 cycle [63:0] $end
$var reg 32 4 fcsr [31:0] $end
$var reg 32 5 fflags [31:0] $end
$var reg 32 6 frm [31:0] $end
$var reg 64 7 instret [63:0] $end
$var reg 32 8 marchid [31:0] $end
$var reg 32 9 mcause [31:0] $end
$var reg 32 : mepc [31:0] $end
$var reg 32 ; mhartid [31:0] $end
$var reg 32 < mie [31:0] $end
$var reg 32 = mimpid [31:0] $end
$var reg 32 > mip [31:0] $end
$var reg 32 ? misa [31:0] $end
$var reg 32 @ mscratch [31:0] $end
$var reg 32 A mstatus [31:0] $end
$var reg 32 B mtval [31:0] $end
$var reg 32 C mtvec [31:0] $end
$var reg 32 D mvendorid [31:0] $end
$upscope $end
$scope module u_pc_reg $end
$var wire 1 " clk $end
$var wire 1 % hold_flag_i $end
$var wire 32 E jump_addr_i [31:0] $end
$var wire 1 ' jump_flag_i $end
$var wire 32 F pc_o [31:0] $end
$var wire 1 ( rst_n $end
$var reg 32 G pc_reg [31:0] $end
$upscope $end
$scope begin CHECK $end
$upscope $end
$scope begin READ $end
$upscope $end
$scope begin WRITE $end
$upscope $end
$upscope $end
$enddefinitions $end
#0
$dumpvars
bx G
bx F
b0 E
bx D
bx C
bx B
bx A
bx @
bx ?
bx >
bx =
bx <
bx ;
bx :
bx 9
bx 8
bx 7
bx 6
bx 5
bx 4
bx 3
bx 2
bx 1
bx 0
bx /
bx .
z-
bz ,
b0 +
b0 *
0)
x(
0'
b0 &
0%
b0 $
b0 #
0"
bx !
$end
#10000
b0 1
b0 0
b0 /
b0 .
b0 F
b0 G
b0 3
b0 7
b0 !
b0 2
b1 ;
b0 =
b0 8
b0 D
b1000000000000000000000100000000 ?
b0 >
b0 B
b0 9
b0 :
b0 @
b0 C
b0 <
b0 A
b0 4
b0 6
b0 5
0(
1"
#20000
0"
#30000
1"
#40000
0"
#50000
1"
#60000
0"
#70000
1"
#80000
0"
#90000
1"
#100000
0"
1(
#110000
b1 1
b11111111111111111111111111111111 !
b11111111111111111111111111111111 2
b1 3
b100 F
b100 G
1"
#120000
0"
#130000
b10 1
b1000 F
b1000 G
b10 3
1"
#140000
0"
#150000
b11 1
b11 3
b1100 F
b1100 G
1"
#160000
0"
#170000
b100 1
b10000 F
b10000 G
b100 3
1"
#180000
0"
#190000
b101 1
b101 3
b10100 F
b10100 G
1"
#200000
0"
#210000
b110 1
b11000 F
b11000 G
b110 3
1"
#220000
0"
#230000
b111 1
b111 3
b11100 F
b11100 G
1"
#240000
0"
#250000
b1000 1
b100000 F
b100000 G
b1000 3
1"
#260000
0"
#270000
b1001 1
b1001 3
b100100 F
b100100 G
1"
#280000
0"
#290000
b1010 1
b101000 F
b101000 G
b1010 3
1"
#300000
0"
#310000
b1011 1
b1011 3
b101100 F
b101100 G
1"
#320000
0"
#330000
b1100 1
b110000 F
b110000 G
b1100 3
1"
#340000
0"
#350000
b1101 1
b1101 3
b110100 F
b110100 G
1"
#360000
0"
#370000
b1110 1
b111000 F
b111000 G
b1110 3
1"
#380000
0"
#390000
b1111 1
b1111 3
b111100 F
b111100 G
1"
#400000
0"
#410000
b10000 1
b1000000 F
b1000000 G
b10000 3
1"
#420000
0"
#430000
b10001 1
b10001 3
b1000100 F
b1000100 G
1"
#440000
0"
#450000
b10010 1
b1001000 F
b1001000 G
b10010 3
1"
#460000
0"
#470000
b10011 1
b10011 3
b1001100 F
b1001100 G
1"
#480000
0"
#490000
b10100 1
b1010000 F
b1010000 G
b10100 3
1"
#500000
0"
#510000
b10101 1
b10101 3
b1010100 F
b1010100 G
1"
#520000
0"
#530000
b10110 1
b1011000 F
b1011000 G
b10110 3
1"
#540000
0"
#550000
b10111 1
b10111 3
b1011100 F
b1011100 G
1"
#560000
0"
#570000
b11000 1
b1100000 F
b1100000 G
b11000 3
1"
#580000
0"
#590000
b11001 1
b11001 3
b1100100 F
b1100100 G
1"
#600000
0"
#610000
b11010 1
b1101000 F
b1101000 G
b11010 3
1"
#620000
0"
#630000
b11011 1
b11011 3
b1101100 F
b1101100 G
1"
#640000
0"
#650000
b11100 1
b1110000 F
b1110000 G
b11100 3
1"
#660000
0"
#670000
b11101 1
b11101 3
b1110100 F
b1110100 G
1"
#680000
0"
#690000
b11110 1
b1111000 F
b1111000 G
b11110 3
1"
#700000
0"
#710000
b11111 1
b11111 3
b1111100 F
b1111100 G
1"
#720000
0"
#730000
b100000 1
b10000000 F
b10000000 G
b100000 3
1"
#740000
0"
#750000
b100001 1
b100001 3
b10000100 F
b10000100 G
1"
#760000
0"
#770000
b100010 1
b10001000 F
b10001000 G
b100010 3
1"
#780000
0"
#790000
b100011 1
b100011 3
b10001100 F
b10001100 G
1"
#800000
0"
#810000
b100100 1
b10010000 F
b10010000 G
b100100 3
1"
#820000
0"
#830000
b100101 1
b100101 3
b10010100 F
b10010100 G
1"
#840000
0"
#850000
b100110 1
b10011000 F
b10011000 G
b100110 3
1"
#860000
0"
#870000
b100111 1
b100111 3
b10011100 F
b10011100 G
1"
#880000
0"
#890000
b101000 1
b10100000 F
b10100000 G
b101000 3
1"
#900000
0"
#910000
b101001 1
b101001 3
b10100100 F
b10100100 G
1"
#920000
0"
#930000
b101010 1
b10101000 F
b10101000 G
b101010 3
1"
#940000
0"
#950000
b101011 1
b101011 3
b10101100 F
b10101100 G
1"
#960000
0"
#970000
b101100 1
b10110000 F
b10110000 G
b101100 3
1"
#980000
0"
#990000
b101101 1
b101101 3
b10110100 F
b10110100 G
1"
#1000000
0"
1%
#1010000
b101110 1
b101110 3
1"
#1020000
0"
#1030000
b101111 1
b101111 3
1"
#1040000
0"
#1050000
b110000 1
b110000 3
1"
#1060000
0"
#1070000
b110001 1
b110001 3
1"
#1080000
0"
#1090000
b110010 1
b110010 3
1"
#1100000
0"
#1110000
b110011 1
b110011 3
1"
#1120000
0"
#1130000
b110100 1
b110100 3
1"
#1140000
0"
#1150000
b110101 1
b110101 3
1"
#1160000
0"
#1170000
b110110 1
b110110 3
1"
#1180000
0"
#1190000
b110111 1
b110111 3
1"
#1200000
0"
#1210000
b111000 1
b111000 3
1"
#1220000
0"
#1230000
b111001 1
b111001 3
1"
#1240000
0"
#1250000
b111010 1
b111010 3
1"
#1260000
0"
#1270000
b111011 1
b111011 3
1"
#1280000
0"
#1290000
b111100 1
b111100 3
1"
#1300000
0"
#1310000
b111101 1
b111101 3
1"
#1320000
0"
#1330000
b111110 1
b111110 3
1"
#1340000
0"
#1350000
b111111 1
b111111 3
1"
#1360000
0"
#1370000
b1000000 1
b1000000 3
1"
#1380000
0"
#1390000
b1000001 1
b1000001 3
1"
#1400000
0"
#1410000
b1000010 1
b1000010 3
1"
#1420000
0"
#1430000
b1000011 1
b1000011 3
1"
#1440000
0"
#1450000
b1000100 1
b1000100 3
1"
#1460000
0"
#1470000
b1000101 1
b1000101 3
1"
#1480000
0"
#1490000
b1000110 1
b1000110 3
1"
#1500000
0"
#1510000
b1000111 1
b1000111 3
1"
#1520000
0"
#1530000
b1001000 1
b1001000 3
1"
#1540000
0"
#1550000
b1001001 1
b1001001 3
1"
#1560000
0"
#1570000
b1001010 1
b1001010 3
1"
#1580000
0"
#1590000
b1001011 1
b1001011 3
1"
#1600000
0"
#1610000
b1001100 1
b1001100 3
1"
#1620000
0"
#1630000
b1001101 1
b1001101 3
1"
#1640000
0"
#1650000
b1001110 1
b1001110 3
1"
#1660000
0"
#1670000
b1001111 1
b1001111 3
1"
#1680000
0"
#1690000
b1010000 1
b1010000 3
1"
#1700000
0"
#1710000
b1010001 1
b1010001 3
1"
#1720000
0"
#1730000
b1010010 1
b1010010 3
1"
#1740000
0"
#1750000
b1010011 1
b1010011 3
1"
#1760000
0"
#1770000
b1010100 1
b1010100 3
1"
#1780000
0"
#1790000
b1010101 1
b1010101 3
1"
#1800000
0"
#1810000
b1010110 1
b1010110 3
1"
#1820000
0"
#1830000
b1010111 1
b1010111 3
1"
#1840000
0"
#1850000
b1011000 1
b1011000 3
1"
#1860000
0"
#1870000
b1011001 1
b1011001 3
1"
#1880000
0"
#1890000
b1011010 1
b1011010 3
1"
#1900000
0"
#1910000
b1011011 1
b1011011 3
1"
#1920000
0"
#1930000
b1011100 1
b1011100 3
1"
#1940000
0"
#1950000
b1011101 1
b1011101 3
1"
#1960000
0"
#1970000
b1011110 1
b1011110 3
1"
#1980000
0"
#1990000
b1011111 1
b1011111 3
1"
#2000000
0"
#2010000
b1100000 1
b1100000 3
1"
#2020000
0"
#2030000
b1100001 1
b1100001 3
1"
#2040000
0"
#2050000
b1100010 1
b1100010 3
1"
#2060000
0"
#2070000
b1100011 1
b1100011 3
1"
#2080000
0"
#2090000
b1100100 1
b1100100 3
1"
#2100000
0"
#2110000
b1100101 1
b1100101 3
1"
#2120000
0"
#2130000
b1100110 1
b1100110 3
1"
#2140000
0"
#2150000
b1100111 1
b1100111 3
1"
#2160000
0"
#2170000
b1101000 1
b1101000 3
1"
#2180000
0"
#2190000
b1101001 1
b1101001 3
1"
#2200000
0"
#2210000
b1101010 1
b1101010 3
1"
#2220000
0"
#2230000
b1101011 1
b1101011 3
1"
#2240000
0"
#2250000
b1101100 1
b1101100 3
1"
#2260000
0"
#2270000
b1101101 1
b1101101 3
1"
#2280000
0"
#2290000
b1101110 1
b1101110 3
1"
#2300000
0"
#2310000
b1101111 1
b1101111 3
1"
#2320000
0"
#2330000
b1110000 1
b1110000 3
1"
#2340000
0"
#2350000
b1110001 1
b1110001 3
1"
#2360000
0"
#2370000
b1110010 1
b1110010 3
1"
#2380000
0"
#2390000
b1110011 1
b1110011 3
1"
#2400000
0"
#2410000
b1110100 1
b1110100 3
1"
#2420000
0"
#2430000
b1110101 1
b1110101 3
1"
#2440000
0"
#2450000
b1110110 1
b1110110 3
1"
#2460000
0"
#2470000
b1110111 1
b1110111 3
1"
#2480000
0"
#2490000
b1111000 1
b1111000 3
1"
#2500000
0"
#2510000
b1111001 1
b1111001 3
1"
#2520000
0"
#2530000
b1111010 1
b1111010 3
1"
#2540000
0"
#2550000
b1111011 1
b1111011 3
1"
#2560000
0"
#2570000
b1111100 1
b1111100 3
1"
#2580000
0"
#2590000
b1111101 1
b1111101 3
1"
#2600000
0"
#2610000
b1111110 1
b1111110 3
1"
#2620000
0"
#2630000
b1111111 1
b1111111 3
1"
#2640000
0"
#2650000
b10000000 1
b10000000 3
1"
#2660000
0"
#2670000
b10000001 1
b10000001 3
1"
#2680000
0"
#2690000
b10000010 1
b10000010 3
1"
#2700000
0"
#2710000
b10000011 1
b10000011 3
1"
#2720000
0"
#2730000
b10000100 1
b10000100 3
1"
#2740000
0"
#2750000
b10000101 1
b10000101 3
1"
#2760000
0"
#2770000
b10000110 1
b10000110 3
1"
#2780000
0"
#2790000
b10000111 1
b10000111 3
1"
#2800000
0"
#2810000
b10001000 1
b10001000 3
1"
#2820000
0"
#2830000
b10001001 1
b10001001 3
1"
#2840000
0"
#2850000
b10001010 1
b10001010 3
1"
#2860000
0"
#2870000
b10001011 1
b10001011 3
1"
#2880000
0"
#2890000
b10001100 1
b10001100 3
1"
#2900000
0"
#2910000
b10001101 1
b10001101 3
1"
#2920000
0"
#2930000
b10001110 1
b10001110 3
1"
#2940000
0"
#2950000
b10001111 1
b10001111 3
1"
#2960000
0"
#2970000
b10010000 1
b10010000 3
1"
#2980000
0"
#2990000
b10010001 1
b10010001 3
1"
#3000000
0"
0%
#3010000
b10010010 1
b10111000 F
b10111000 G
b10010010 3
1"
#3020000
0"
#3030000
b10010011 1
b10010011 3
b10111100 F
b10111100 G
1"
#3040000
0"
#3050000
b10010100 1
b11000000 F
b11000000 G
b10010100 3
1"
#3060000
0"
#3070000
b10010101 1
b10010101 3
b11000100 F
b11000100 G
1"
#3080000
0"
#3090000
b10010110 1
b11001000 F
b11001000 G
b10010110 3
1"
#3100000
0"
#3110000
b10010111 1
b10010111 3
b11001100 F
b11001100 G
1"
#3120000
0"
#3130000
b10011000 1
b11010000 F
b11010000 G
b10011000 3
1"
#3140000
0"
#3150000
b10011001 1
b10011001 3
b11010100 F
b11010100 G
1"
#3160000
0"
#3170000
b10011010 1
b11011000 F
b11011000 G
b10011010 3
1"
#3180000
0"
#3190000
b10011011 1
b10011011 3
b11011100 F
b11011100 G
1"
#3200000
0"
#3210000
b10011100 1
b11100000 F
b11100000 G
b10011100 3
1"
#3220000
0"
#3230000
b10011101 1
b10011101 3
b11100100 F
b11100100 G
1"
#3240000
0"
#3250000
b10011110 1
b11101000 F
b11101000 G
b10011110 3
1"
#3260000
0"
#3270000
b10011111 1
b10011111 3
b11101100 F
b11101100 G
1"
#3280000
0"
#3290000
b10100000 1
b11110000 F
b11110000 G
b10100000 3
1"
#3300000
0"
#3310000
b10100001 1
b10100001 3
b11110100 F
b11110100 G
1"
#3320000
0"
#3330000
b10100010 1
b11111000 F
b11111000 G
b10100010 3
1"
#3340000
0"
#3350000
b10100011 1
b10100011 3
b11111100 F
b11111100 G
1"
#3360000
0"
#3370000
b10100100 1
b100000000 F
b100000000 G
b10100100 3
1"
#3380000
0"
#3390000
b10100101 1
b10100101 3
b100000100 F
b100000100 G
1"
#3400000
0"
#3410000
b10100110 1
b100001000 F
b100001000 G
b10100110 3
1"
#3420000
0"
#3430000
b10100111 1
b10100111 3
b100001100 F
b100001100 G
1"
#3440000
0"
#3450000
b10101000 1
b100010000 F
b100010000 G
b10101000 3
1"
#3460000
0"
#3470000
b10101001 1
b10101001 3
b100010100 F
b100010100 G
1"
#3480000
0"
#3490000
b10101010 1
b100011000 F
b100011000 G
b10101010 3
1"
#3500000
0"
#3510000
b10101011 1
b10101011 3
b100011100 F
b100011100 G
1"
#3520000
0"
#3530000
b10101100 1
b100100000 F
b100100000 G
b10101100 3
1"
#3540000
0"
#3550000
b10101101 1
b10101101 3
b100100100 F
b100100100 G
1"
#3560000
0"
#3570000
b10101110 1
b100101000 F
b100101000 G
b10101110 3
1"
#3580000
0"
#3590000
b10101111 1
b10101111 3
b100101100 F
b100101100 G
1"
#3600000
0"
#3610000
b10110000 1
b100110000 F
b100110000 G
b10110000 3
1"
#3620000
0"
#3630000
b10110001 1
b10110001 3
b100110100 F
b100110100 G
1"
#3640000
0"
#3650000
b10110010 1
b100111000 F
b100111000 G
b10110010 3
1"
#3660000
0"
#3670000
b10110011 1
b10110011 3
b100111100 F
b100111100 G
1"
#3680000
0"
#3690000
b10110100 1
b101000000 F
b101000000 G
b10110100 3
1"
#3700000
0"
#3710000
b10110101 1
b10110101 3
b101000100 F
b101000100 G
1"
#3720000
0"
#3730000
b10110110 1
b101001000 F
b101001000 G
b10110110 3
1"
#3740000
0"
#3750000
b10110111 1
b10110111 3
b101001100 F
b101001100 G
1"
#3760000
0"
#3770000
b10111000 1
b101010000 F
b101010000 G
b10111000 3
1"
#3780000
0"
#3790000
b10111001 1
b10111001 3
b101010100 F
b101010100 G
1"
#3800000
0"
#3810000
b10111010 1
b101011000 F
b101011000 G
b10111010 3
1"
#3820000
0"
#3830000
b10111011 1
b10111011 3
b101011100 F
b101011100 G
1"
#3840000
0"
#3850000
b10111100 1
b101100000 F
b101100000 G
b10111100 3
1"
#3860000
0"
#3870000
b10111101 1
b10111101 3
b101100100 F
b101100100 G
1"
#3880000
0"
#3890000
b10111110 1
b101101000 F
b101101000 G
b10111110 3
1"
#3900000
0"
#3910000
b10111111 1
b10111111 3
b101101100 F
b101101100 G
1"
#3920000
0"
#3930000
b11000000 1
b101110000 F
b101110000 G
b11000000 3
1"
#3940000
0"
#3950000
b11000001 1
b11000001 3
b101110100 F
b101110100 G
1"
#3960000
0"
#3970000
b11000010 1
b101111000 F
b101111000 G
b11000010 3
1"
#3980000
0"
#3990000
b11000011 1
b11000011 3
b101111100 F
b101111100 G
1"
#4000000
0"
#4010000
b11000100 1
b110000000 F
b110000000 G
b11000100 3
1"
#4020000
0"
#4030000
b11000101 1
b11000101 3
b110000100 F
b110000100 G
1"
#4040000
0"
#4050000
b11000110 1
b110001000 F
b110001000 G
b11000110 3
1"
#4060000
0"
#4070000
b11000111 1
b11000111 3
b110001100 F
b110001100 G
1"
#4080000
0"
#4090000
b11001000 1
b110010000 F
b110010000 G
b11001000 3
1"
#4100000
0"
#4110000
b11001001 1
b11001001 3
b110010100 F
b110010100 G
1"
#4120000
0"
#4130000
b11001010 1
b110011000 F
b110011000 G
b11001010 3
1"
#4140000
0"
#4150000
b11001011 1
b11001011 3
b110011100 F
b110011100 G
1"
#4160000
0"
#4170000
b11001100 1
b110100000 F
b110100000 G
b11001100 3
1"
#4180000
0"
#4190000
b11001101 1
b11001101 3
b110100100 F
b110100100 G
1"
#4200000
0"
#4210000
b11001110 1
b110101000 F
b110101000 G
b11001110 3
1"
#4220000
0"
#4230000
b11001111 1
b11001111 3
b110101100 F
b110101100 G
1"
#4240000
0"
#4250000
b11010000 1
b110110000 F
b110110000 G
b11010000 3
1"
#4260000
0"
#4270000
b11010001 1
b11010001 3
b110110100 F
b110110100 G
1"
#4280000
0"
#4290000
b11010010 1
b110111000 F
b110111000 G
b11010010 3
1"
#4300000
0"
#4310000
b11010011 1
b11010011 3
b110111100 F
b110111100 G
1"
#4320000
0"
#4330000
b11010100 1
b111000000 F
b111000000 G
b11010100 3
1"
#4340000
0"
#4350000
b11010101 1
b11010101 3
b111000100 F
b111000100 G
1"
#4360000
0"
#4370000
b11010110 1
b111001000 F
b111001000 G
b11010110 3
1"
